setup.py
packeges_test/__init__.py
packeges_test.egg-info/PKG-INFO
packeges_test.egg-info/SOURCES.txt
packeges_test.egg-info/dependency_links.txt
packeges_test.egg-info/not-zip-safe
packeges_test.egg-info/top_level.txt