Metadata-Version: 1.0
Name: packeges-test
Version: 0.1
Summary: The funniest joke in the world
Home-page: http://github.com/ddi-pc-57/packeges_test
Author: Flying Circus
Author-email: packeges_test@example.com
License: MIT
Platform: UNKNOWN
